{
    "imagePath": "00016.jpg",
    "imageHeight": 3888,
    "imageWidth": 5184,
    "lps": [
        {
            "lp_id": "AN-4*73B*W",
            "poly_coord": [
                [
                    919,
                    2405
                ],
                [
                    1745,
                    2556
                ],
                [
                    1740,
                    2763
                ],
                [
                    929,
                    2594
                ]
            ],
            "characters": [
                {
                    "char_id": "4",
                    "bbox_coord": [
                        [
                            1019,
                            2443
                        ],
                        [
                            1101,
                            2614
                        ]
                    ]
                },
                {
                    "char_id": "7",
                    "bbox_coord": [
                        [
                            1191,
                            2470
                        ],
                        [
                            1266,
                            2654
                        ]
                    ]
                },
                {
                    "char_id": "3",
                    "bbox_coord": [
                        [
                            1285,
                            2496
                        ],
                        [
                            1370,
                            2670
                        ]
                    ]
                },
                {
                    "char_id": "B",
                    "bbox_coord": [
                        [
                            1428,
                            2508
                        ],
                        [
                            1510,
                            2694
                        ]
                    ]
                },
                {
                    "char_id": "W",
                    "bbox_coord": [
                        [
                            1615,
                            2549
                        ],
                        [
                            1710,
                            2740
                        ]
                    ]
                }
            ]
        }
    ]
}