{
    "imagePath": "00268.jpg",
    "imageHeight": 3888,
    "imageWidth": 5184,
    "lps": [
        {
            "lp_id": "AD-*155*DW",
            "poly_coord": [
                [
                    2667,
                    2096
                ],
                [
                    2903,
                    2088
                ],
                [
                    2903,
                    2144
                ],
                [
                    2665,
                    2148
                ]
            ],
            "characters": [
                {
                    "char_id": "1",
                    "bbox_coord": [
                        [
                            2723,
                            2096
                        ],
                        [
                            2739,
                            2142
                        ]
                    ]
                },
                {
                    "char_id": "5",
                    "bbox_coord": [
                        [
                            2744,
                            2096
                        ],
                        [
                            2767,
                            2141
                        ]
                    ]
                },
                {
                    "char_id": "5",
                    "bbox_coord": [
                        [
                            2772,
                            2094
                        ],
                        [
                            2797,
                            2142
                        ]
                    ]
                },
                {
                    "char_id": "D",
                    "bbox_coord": [
                        [
                            2841,
                            2092
                        ],
                        [
                            2865,
                            2138
                        ]
                    ]
                },
                {
                    "char_id": "W",
                    "bbox_coord": [
                        [
                            2870,
                            2092
                        ],
                        [
                            2895,
                            2138
                        ]
                    ]
                }
            ]
        }
    ]
}