{
    "imagePath": "00299.jpg",
    "imageHeight": 3888,
    "imageWidth": 5184,
    "lps": [
        {
            "lp_id": "AD-80*8F*B",
            "poly_coord": [
                [
                    2877,
                    2435
                ],
                [
                    3161,
                    2438
                ],
                [
                    3168,
                    2492
                ],
                [
                    2880,
                    2485
                ]
            ],
            "characters": [
                {
                    "char_id": "8",
                    "bbox_coord": [
                        [
                            2909,
                            2439
                        ],
                        [
                            2940,
                            2484
                        ]
                    ]
                },
                {
                    "char_id": "0",
                    "bbox_coord": [
                        [
                            2943,
                            2440
                        ],
                        [
                            2970,
                            2484
                        ]
                    ]
                },
                {
                    "char_id": "8",
                    "bbox_coord": [
                        [
                            3010,
                            2442
                        ],
                        [
                            3038,
                            2484
                        ]
                    ]
                },
                {
                    "char_id": "F",
                    "bbox_coord": [
                        [
                            3054,
                            2440
                        ],
                        [
                            3082,
                            2484
                        ]
                    ]
                },
                {
                    "char_id": "B",
                    "bbox_coord": [
                        [
                            3123,
                            2442
                        ],
                        [
                            3151,
                            2487
                        ]
                    ]
                }
            ]
        }
    ]
}